aiocapsolver/__init__.py
aiocapsolver/capsolver.py
aiocapsolver/captcha_error.py
aiocapsolver/solution.py
aiocapsolver-0.0.2.dist-info/LICENSE
aiocapsolver-0.0.2.dist-info/METADATA
aiocapsolver-0.0.2.dist-info/WHEEL
aiocapsolver-0.0.2.dist-info/top_level.txt
aiocapsolver-0.0.2.dist-info/RECORD
