Metadata-Version: 2.1
Name: aiocapsolver
Version: 0.0.2
Summary: Async API wrapper for capsolver.com
Home-page: UNKNOWN
Author: Eli Chandler
Author-email: eli.chandler@gmail.com
License: UNKNOWN
Keywords: python,captcha,solver,capsolver,api,wrapper
Platform: UNKNOWN
Classifier: Development Status :: 4 - Beta
Classifier: Intended Audience :: Developers
Classifier: Programming Language :: Python :: 3
Classifier: Operating System :: Unix
Classifier: Operating System :: MacOS :: MacOS X
Classifier: Operating System :: Microsoft :: Windows
License-File: LICENSE
Requires-Dist: aiofiles
Requires-Dist: aiohttp
Requires-Dist: aiosignal
Requires-Dist: async-timeout
Requires-Dist: attrs
Requires-Dist: build
Requires-Dist: charset-normalizer
Requires-Dist: colorama
Requires-Dist: filelock
Requires-Dist: frozenlist
Requires-Dist: idna
Requires-Dist: multidict
Requires-Dist: packaging
Requires-Dist: platformdirs
Requires-Dist: pyproject-hooks
Requires-Dist: tomli
Requires-Dist: uritools
Requires-Dist: urlextract
Requires-Dist: urllib3
Requires-Dist: yarl
